KratosMultiphysics/ContactStructuralMechanicsApplication/__init__.py
KratosMultiphysics/ContactStructuralMechanicsApplication/alm_contact_process.py
KratosMultiphysics/ContactStructuralMechanicsApplication/auxiliary_methods_solvers.py
KratosMultiphysics/ContactStructuralMechanicsApplication/basic_mapping_process.py
KratosMultiphysics/ContactStructuralMechanicsApplication/contact_convergence_criteria_factory.py
KratosMultiphysics/ContactStructuralMechanicsApplication/contact_remesh_mmg_process.py
KratosMultiphysics/ContactStructuralMechanicsApplication/contact_structural_mechanics_explicit_dynamic_solver.py
KratosMultiphysics/ContactStructuralMechanicsApplication/contact_structural_mechanics_implicit_dynamic_solver.py
KratosMultiphysics/ContactStructuralMechanicsApplication/contact_structural_mechanics_static_solver.py
KratosMultiphysics/ContactStructuralMechanicsApplication/custom_sympy_fe_utilities.py
KratosMultiphysics/ContactStructuralMechanicsApplication/explicit_penalty_contact_process.py
KratosMultiphysics/ContactStructuralMechanicsApplication/mesh_tying_process.py
KratosMultiphysics/ContactStructuralMechanicsApplication/mpc_contact_process.py
KratosMultiphysics/ContactStructuralMechanicsApplication/mpc_contact_structural_mechanics_implicit_dynamic_solver.py
KratosMultiphysics/ContactStructuralMechanicsApplication/mpc_contact_structural_mechanics_static_solver.py
KratosMultiphysics/ContactStructuralMechanicsApplication/penalty_contact_process.py
KratosMultiphysics/ContactStructuralMechanicsApplication/python_solvers_wrapper_adaptative_remeshing_contact_structural.py
KratosMultiphysics/ContactStructuralMechanicsApplication/replace_properties_process.py
KratosMultiphysics/ContactStructuralMechanicsApplication/search_base_process.py
KratosMultiphysics/ContactStructuralMechanicsApplication/adaptive_remeshing/adaptative_remeshing_contact_structural_mechanics_analysis.py
kratoscontactstructuralmechanicsapplication-10.4.0.dist-info/METADATA
kratoscontactstructuralmechanicsapplication-10.4.0.dist-info/WHEEL
kratoscontactstructuralmechanicsapplication-10.4.0.dist-info/RECORD
