Metadata-Version: 2.4
Name: KratosContactStructuralMechanicsApplication
Version: 10.4.0
Summary: The Contact Structural Mechanics Application contains the contact mechanics implementations that can be used by the Structural Mechanics Application within Kratos Multiphysics.
Author-email: Vicente Mataix Ferrándiz <vmataix@altair.com>
License: BSD-4-Clause
Classifier: Programming Language :: C++
Classifier: Programming Language :: Python :: 3
Classifier: Topic :: Scientific/Engineering
Requires-Python: >=3.8
Requires-Dist: kratosmultiphysics==10.4.0
Requires-Dist: kratosstructuralmechanicsapplication==10.4.0
